air/__init__.py
air/aircv/__init__.py
air/aircv/aircv.py
air/aircv/cal_confidence.py
air/aircv/error.py
air/aircv/keypoint_base.py
air/aircv/keypoint_matching.py
air/aircv/keypoint_matching_contrib.py
air/aircv/sift.py
air/aircv/template.py
air/aircv/template_matching.py
air/aircv/utils.py
air/tests/__init__.py
air/tests/test_aircv.py
cli/__init__.py
cli/android.py
cli/cli.py
auto_util-0.1.dist-info/METADATA
auto_util-0.1.dist-info/WHEEL
auto_util-0.1.dist-info/entry_points.txt
auto_util-0.1.dist-info/top_level.txt
auto_util-0.1.dist-info/RECORD
