Metadata-Version: 2.1
Name: auto-util
Version: 0.1
Summary: A command line tool for image matching
Home-page: https://github.com/auto-flutter/auto_util
License: Apache License 2.0
Platform: UNKNOWN
Classifier: Programming Language :: Python :: 3.4
Classifier: Programming Language :: Python :: 3.5
Classifier: Programming Language :: Python :: 3.6
Classifier: Programming Language :: Python :: 3.7
Requires-Python: >=3.4,<3.8
Requires-Dist: six
Requires-Dist: click
Requires-Dist: Pillow (>=3.4.0)
Requires-Dist: numpy (<=1.19.3)
Requires-Dist: opencv-contrib-python (==3.4.2.16)
